ovos_skill_config/__init__.py
ovos_skill_config/main.py
ovos_skill_config/version.py
ovos_skill_config/static/config.json
ovos_skill_config/static/favicon.ico
ovos_skill_config/static/index.html
ovos_skill_config/static/logo.svg
ovos_skill_config/static/neon.png
ovos_skill_config/static/assets/index-BU05NY0Y.css
ovos_skill_config/static/assets/index-CLctCwWl.js
ovos_skill_config_tool-0.7.0.dist-info/licenses/LICENSE
ovos_skill_config_tool-0.7.0.dist-info/METADATA
ovos_skill_config_tool-0.7.0.dist-info/WHEEL
ovos_skill_config_tool-0.7.0.dist-info/entry_points.txt
ovos_skill_config_tool-0.7.0.dist-info/top_level.txt
ovos_skill_config_tool-0.7.0.dist-info/RECORD
