Metadata-Version: 2.4
Name: ovos-skill-config-tool
Version: 0.7.0
Summary: OpenVoiceOS/Neon Skills Configuration Tool
Author-email: Oscillate Labs <mike@oscillatelabs.net>
License:                                  Apache License
Project-URL: Homepage, https://github.com/OscillateLabsLLC/ovos-skill-config-tool
Keywords: mycroft,ovos,neon,plugin,configuration,skills,tool
Classifier: Topic :: Text Processing :: Linguistic
Classifier: Programming Language :: Python :: 3
Requires-Python: >=3.9
License-File: LICENSE
Requires-Dist: fastapi>=0.115.6
Requires-Dist: json-database>=0.7.0
Requires-Dist: uvicorn>=0.34.0
Dynamic: license-file
